[{"x":"13.382353%","y":"93.137255%","w":"31.617647%","h":"3.627451%","txt":"<b>РАЗВИТИЕ ЛИЧНОСТИ</b>","style":"font-family: Times; color: #ffffff; font-size: 29;"},{"x":"62.5%","y":"93.823529%","w":"4.852941%","h":"2.352941%","txt":"247","style":"font-family: Times; color: #231f20; font-size: 19;"},{"x":"81.323529%","y":"94.705882%","w":"8.088235%","h":"1.176471%","txt":"<b>№ 4 – 2016</b>","style":"font-family: Times; color: #231f20; font-size: 8;"},{"x":"54.411765%","y":"4.803922%","w":"34.705882%","h":"4.117647%","txt":"<b>Наши авторы</b>","style":"font-family: Times; color: #231f20; font-size: 34;"},{"x":"13.382353%","y":"93.137255%","w":"31.617647%","h":"3.627451%","txt":"<b>РАЗВИТИЕ ЛИЧНОСТИ</b>","style":"font-family: Times; color: #ffffff; font-size: 29;"},{"x":"62.5%","y":"93.72549%","w":"4.852941%","h":"2.352941%","txt":"247","style":"font-family: Times; color: #231f20; font-size: 19;"},{"x":"81.323529%","y":"94.705882%","w":"8.088235%","h":"1.176471%","txt":"<b>№ 4 – 2016</b>","style":"font-family: Times; color: #231f20; font-size: 8;"},{"x":"12.5%","y":"10.392157%","w":"38.235294%","h":"1.568627%","txt":"ный  деятель  науки  Российской ","style":"font-family: Times; color: #231f20; font-size: 13;"},{"x":"12.5%","y":"12.156863%","w":"38.235294%","h":"1.568627%","txt":"Федерации. Руководитель Центра ","style":"font-family: Times; color: #231f20; font-size: 13;"},{"x":"12.5%","y":"13.823529%","w":"38.235294%","h":"1.568627%","txt":"социологии  образования  ФГБНУ ","style":"font-family: Times; color: #231f20; font-size: 13;"},{"x":"12.5%","y":"15.490196%","w":"37.647059%","h":"1.568627%","txt":"«Институт  управления  образова-","style":"font-family: Times; color: #231f20; font-size: 13;"},{"x":"12.5%","y":"17.156863%","w":"37.647059%","h":"1.568627%","txt":"нием Российской академии образо-","style":"font-family: Times; color: #231f20; font-size: 13;"},{"x":"12.5%","y":"18.921569%","w":"8.529412%","h":"1.568627%","txt":"вания».","style":"font-family: Times; color: #231f20; font-size: 13;"},{"x":"12.5%","y":"20.588235%","w":"38.235294%","h":"1.568627%","txt":"Основной круг научных интересов: ","style":"font-family: Times; color: #231f20; font-size: 13;"},{"x":"12.5%","y":"22.254902%","w":"38.235294%","h":"1.568627%","txt":"социология  образования;  детская, ","style":"font-family: Times; color: #231f20; font-size: 13;"},{"x":"12.5%","y":"23.921569%","w":"37.647059%","h":"1.568627%","txt":"возрастная  и  педагогическая  пси-","style":"font-family: Times; color: #231f20; font-size: 13;"},{"x":"12.5%","y":"25.686275%","w":"38.235294%","h":"1.568627%","txt":"хология;  психология  искусства; ","style":"font-family: Times; color: #231f20; font-size: 13;"},{"x":"12.5%","y":"27.352941%","w":"17.794118%","h":"1.568627%","txt":"этнопсихология.","style":"font-family: Times; color: #231f20; font-size: 13;"},{"x":"12.5%","y":"29.019608%","w":"38.235294%","h":"1.568627%","txt":"Автор  более  600  научных  трудов, ","style":"font-family: Times; color: #231f20; font-size: 13;"},{"x":"12.5%","y":"30.686275%","w":"38.235294%","h":"1.568627%","txt":"опубликованных как в России, так ","style":"font-family: Times; color: #231f20; font-size: 13;"},{"x":"12.5%","y":"32.45098%","w":"37.647059%","h":"1.568627%","txt":"и за рубежом. Среди них: моногра-","style":"font-family: Times; color: #231f20; font-size: 13;"},{"x":"12.5%","y":"34.117647%","w":"38.235294%","h":"1.568627%","txt":"фии  по  социальной  психологии,  а ","style":"font-family: Times; color: #231f20; font-size: 13;"},{"x":"12.5%","y":"35.784314%","w":"38.235294%","h":"1.568627%","txt":"также  монография  «Комментарии ","style":"font-family: Times; color: #231f20; font-size: 13;"},{"x":"12.5%","y":"37.45098%","w":"38.235294%","h":"1.568627%","txt":"к  театральным  рецензиям  Льва ","style":"font-family: Times; color: #231f20; font-size: 13;"},{"x":"12.5%","y":"39.215686%","w":"38.235294%","h":"1.568627%","txt":"Выготского  (театральные  статьи  и ","style":"font-family: Times; color: #231f20; font-size: 13;"},{"x":"12.5%","y":"40.882353%","w":"38.235294%","h":"1.568627%","txt":"газетные рецензии, 1917–1923 гг.)». ","style":"font-family: Times; color: #231f20; font-size: 13;"},{"x":"12.5%","y":"42.54902%","w":"11.764706%","h":"1.568627%","txt":"– М., 2015.","style":"font-family: Times; color: #231f20; font-size: 13;"},{"x":"12.5%","y":"44.215686%","w":"38.235294%","h":"1.568627%","txt":"Лауреат  премии  Президента  РФ  в ","style":"font-family: Times; color: #231f20; font-size: 13;"},{"x":"12.5%","y":"45.980392%","w":"23.235294%","h":"1.568627%","txt":"области образования. ","style":"font-family: Times; color: #231f20; font-size: 13;"},{"x":"12.5%","y":"47.647059%","w":"24.558824%","h":"1.568627%","txt":"E-mail: sobkin@mail.ru","style":"font-family: Times; color: #231f20; font-size: 13;"},{"x":"12.5%","y":"50.686275%","w":"20.882353%","h":"1.960784%","txt":"<i><b>VladimirSobkin</b></i>","style":"font-family: Times; color: #231f20; font-size: 16;"},{"x":"12.5%","y":"53.921569%","w":"37.647059%","h":"1.568627%","txt":"Sc.D. (psychology), professor, acade-","style":"font-family: Times; color: #231f20; font-size: 13;"},{"x":"12.5%","y":"55.588235%","w":"37.647059%","h":"1.568627%","txt":"mician of Russian Academy of Edu-","style":"font-family: Times; color: #231f20; font-size: 13;"},{"x":"12.5%","y":"57.254902%","w":"38.235294%","h":"1.568627%","txt":"cation,  Honored  Worker  of  Science ","style":"font-family: Times; color: #231f20; font-size: 13;"},{"x":"12.5%","y":"58.921569%","w":"38.235294%","h":"1.568627%","txt":"of  the  Russian  Federation;  Head  of ","style":"font-family: Times; color: #231f20; font-size: 13;"},{"x":"12.5%","y":"60.686275%","w":"37.647059%","h":"1.568627%","txt":"the Center for the sociology of educa-","style":"font-family: Times; color: #231f20; font-size: 13;"},{"x":"12.5%","y":"62.352941%","w":"38.235294%","h":"1.568627%","txt":"tion, Federal State Budget Scientific ","style":"font-family: Times; color: #231f20; font-size: 13;"},{"x":"12.5%","y":"64.019608%","w":"38.235294%","h":"1.568627%","txt":"Institution  “Institute  of  Education ","style":"font-family: Times; color: #231f20; font-size: 13;"},{"x":"12.5%","y":"65.686275%","w":"37.647059%","h":"1.568627%","txt":"Management of the Russian Acade-","style":"font-family: Times; color: #231f20; font-size: 13;"},{"x":"12.5%","y":"67.45098%","w":"18.529412%","h":"1.568627%","txt":"my of Education”.","style":"font-family: Times; color: #231f20; font-size: 13;"},{"x":"12.5%","y":"69.117647%","w":"38.235294%","h":"1.568627%","txt":"The author of more than 600 works, ","style":"font-family: Times; color: #231f20; font-size: 13;"},{"x":"12.5%","y":"70.784314%","w":"32.5%","h":"1.568627%","txt":"published in Russia and abroad.","style":"font-family: Times; color: #231f20; font-size: 13;"},{"x":"12.5%","y":"72.45098%","w":"38.235294%","h":"1.568627%","txt":"Laureate of President of the Russian ","style":"font-family: Times; color: #231f20; font-size: 13;"},{"x":"12.5%","y":"74.215686%","w":"37.647059%","h":"1.568627%","txt":"Federation Prize in the Field of Edu-","style":"font-family: Times; color: #231f20; font-size: 13;"},{"x":"12.5%","y":"75.882353%","w":"7.5%","h":"1.568627%","txt":"cation. ","style":"font-family: Times; color: #231f20; font-size: 13;"},{"x":"12.5%","y":"78.921569%","w":"22.352941%","h":"1.960784%","txt":"<i><b>ЯРОШЕВСКИЙ</b></i>","style":"font-family: Times; color: #231f20; font-size: 16;"},{"x":"12.5%","y":"80.980392%","w":"28.676471%","h":"1.960784%","txt":"<i><b>МихаилГригорьевич</b></i>","style":"font-family: Times; color: #231f20; font-size: 16;"},{"x":"12.5%","y":"83.039216%","w":"33.382353%","h":"1.960784%","txt":"<i><b>(22.08.1915–22.03.2001)</b></i>","style":"font-family: Times; color: #231f20; font-size: 16;"},{"x":"12.5%","y":"86.27451%","w":"38.235294%","h":"1.568627%","txt":"Доктор  психологических  наук, ","style":"font-family: Times; color: #231f20; font-size: 13;"},{"x":"12.5%","y":"87.941176%","w":"38.235294%","h":"1.568627%","txt":"профессор,  почетный  академик ","style":"font-family: Times; color: #231f20; font-size: 13;"},{"x":"12.5%","y":"89.607843%","w":"38.235294%","h":"1.568627%","txt":"РАО, главный научный сотрудник ","style":"font-family: Times; color: #231f20; font-size: 13;"},{"x":"52.794118%","y":"10.392157%","w":"38.235294%","h":"1.568627%","txt":"Института истории естествознания ","style":"font-family: Times; color: #231f20; font-size: 13;"},{"x":"52.794118%","y":"12.156863%","w":"17.205882%","h":"1.568627%","txt":"и техники РАН.","style":"font-family: Times; color: #231f20; font-size: 13;"},{"x":"52.794118%","y":"13.823529%","w":"38.235294%","h":"1.568627%","txt":"Сферы  исследований:  история ","style":"font-family: Times; color: #231f20; font-size: 13;"},{"x":"52.794118%","y":"15.490196%","w":"38.235294%","h":"1.568627%","txt":"науки  (в  частности,  психология), ","style":"font-family: Times; color: #231f20; font-size: 13;"},{"x":"52.794118%","y":"17.156863%","w":"37.647059%","h":"1.568627%","txt":"психолингвистика, теория и мето-","style":"font-family: Times; color: #231f20; font-size: 13;"},{"x":"52.794118%","y":"18.921569%","w":"38.235294%","h":"1.568627%","txt":"дология  психологии,  психология ","style":"font-family: Times; color: #231f20; font-size: 13;"},{"x":"52.794118%","y":"20.588235%","w":"38.235294%","h":"1.568627%","txt":"творчества.  Автор  монографий: ","style":"font-family: Times; color: #231f20; font-size: 13;"},{"x":"52.794118%","y":"22.254902%","w":"37.647059%","h":"1.568627%","txt":"Проблемы  детерминизма  в  психо-","style":"font-family: Times; color: #231f20; font-size: 13;"},{"x":"52.794118%","y":"23.921569%","w":"38.235294%","h":"1.568627%","txt":"физиологии  XIX  в.  –  М.,  1961; ","style":"font-family: Times; color: #231f20; font-size: 13;"},{"x":"52.794118%","y":"25.686275%","w":"38.235294%","h":"1.568627%","txt":"История  психологии.  –  3-е  изд., ","style":"font-family: Times; color: #231f20; font-size: 13;"},{"x":"52.794118%","y":"27.352941%","w":"38.235294%","h":"1.568627%","txt":"перераб.  –  М.,  1985;  Сеченов  и ","style":"font-family: Times; color: #231f20; font-size: 13;"},{"x":"52.794118%","y":"29.019608%","w":"38.235294%","h":"1.568627%","txt":"мировая психологическая мысль. – ","style":"font-family: Times; color: #231f20; font-size: 13;"},{"x":"52.794118%","y":"30.686275%","w":"38.235294%","h":"1.568627%","txt":"М., 1981; Психология в XX в. – М., ","style":"font-family: Times; color: #231f20; font-size: 13;"},{"x":"52.794118%","y":"32.45098%","w":"38.235294%","h":"1.568627%","txt":"1990;  Психология:  учебник  для ","style":"font-family: Times; color: #231f20; font-size: 13;"},{"x":"52.794118%","y":"34.117647%","w":"38.235294%","h":"1.568627%","txt":"студ. высш. пед. учеб. заведений (в ","style":"font-family: Times; color: #231f20; font-size: 13;"},{"x":"52.794118%","y":"35.784314%","w":"38.235294%","h":"1.568627%","txt":"соавторстве с А.В. Петровским). – ","style":"font-family: Times; color: #231f20; font-size: 13;"},{"x":"52.794118%","y":"37.45098%","w":"38.235294%","h":"1.568627%","txt":"М.,  1998;  Основы  теоретической ","style":"font-family: Times; color: #231f20; font-size: 13;"},{"x":"52.794118%","y":"39.215686%","w":"38.235294%","h":"1.568627%","txt":"психологии  (в  соавторстве  с ","style":"font-family: Times; color: #231f20; font-size: 13;"},{"x":"52.794118%","y":"40.882353%","w":"37.647059%","h":"1.568627%","txt":"А.В.  Петровским  и  В.А.  Петров-","style":"font-family: Times; color: #231f20; font-size: 13;"},{"x":"52.794118%","y":"42.54902%","w":"9.852941%","h":"1.568627%","txt":"ским;  бо","style":"font-family: Times; color: #231f20; font-size: 13;"},{"x":"62.794118%","y":"42.54902%","w":"28.235294%","h":"1.862745%","txt":"́льшая  часть  книги  (гл. ","style":"font-family: Times; color: #231f20; font-size: 13;"},{"x":"52.794118%","y":"44.215686%","w":"38.235294%","h":"1.568627%","txt":"1–8,  12,  13,  15–17)  написана ","style":"font-family: Times; color: #231f20; font-size: 13;"},{"x":"52.794118%","y":"45.980392%","w":"38.235294%","h":"1.568627%","txt":"М.Г.  Ярошевским).  –  М.,  1998; ","style":"font-family: Times; color: #231f20; font-size: 13;"},{"x":"52.794118%","y":"47.647059%","w":"38.235294%","h":"1.568627%","txt":"Л.С.  Выготский:  в  поисках  новой ","style":"font-family: Times; color: #231f20; font-size: 13;"},{"x":"52.794118%","y":"49.313725%","w":"38.235294%","h":"1.568627%","txt":"психологии. – СПб., 1993; История ","style":"font-family: Times; color: #231f20; font-size: 13;"},{"x":"52.794118%","y":"50.980392%","w":"37.647059%","h":"1.568627%","txt":"психологии. От античности до сере-","style":"font-family: Times; color: #231f20; font-size: 13;"},{"x":"52.794118%","y":"52.745098%","w":"38.235294%","h":"1.568627%","txt":"дины  ХХ  века:  учеб.  пособие  для ","style":"font-family: Times; color: #231f20; font-size: 13;"},{"x":"52.794118%","y":"54.411765%","w":"38.235294%","h":"1.568627%","txt":"высш. учеб. заведений. – 2-е изд. – ","style":"font-family: Times; color: #231f20; font-size: 13;"},{"x":"52.794118%","y":"56.078431%","w":"9.852941%","h":"1.568627%","txt":"М., 1997.","style":"font-family: Times; color: #231f20; font-size: 13;"},{"x":"52.794118%","y":"59.117647%","w":"27.205882%","h":"1.960784%","txt":"<i><b>MikhailJaroshevsky</b></i>","style":"font-family: Times; color: #231f20; font-size: 16;"},{"x":"52.794118%","y":"61.176471%","w":"33.382353%","h":"1.960784%","txt":"<i><b>(22.08.1915–22.03.2001)</b></i>","style":"font-family: Times; color: #231f20; font-size: 16;"},{"x":"52.794118%","y":"64.411765%","w":"37.647059%","h":"1.568627%","txt":"Sc.D.  (psychology),  professor,  hon-","style":"font-family: Times; color: #231f20; font-size: 13;"},{"x":"52.794118%","y":"66.078431%","w":"38.235294%","h":"1.568627%","txt":"ored  academician  of  RAE  (academy ","style":"font-family: Times; color: #231f20; font-size: 13;"},{"x":"52.794118%","y":"67.745098%","w":"38.235294%","h":"1.568627%","txt":"of  education),  leading  scientific ","style":"font-family: Times; color: #231f20; font-size: 13;"},{"x":"52.794118%","y":"69.509804%","w":"38.235294%","h":"1.568627%","txt":"researcher in Institute of History of ","style":"font-family: Times; color: #231f20; font-size: 13;"},{"x":"52.794118%","y":"71.176471%","w":"38.235294%","h":"1.568627%","txt":"Natural  Sciences  and  Technology, ","style":"font-family: Times; color: #231f20; font-size: 13;"},{"x":"52.794118%","y":"72.843137%","w":"38.235294%","h":"1.568627%","txt":"RAS.  Sphere  of  M.  Yaroshevcky’s ","style":"font-family: Times; color: #231f20; font-size: 13;"},{"x":"52.794118%","y":"74.509804%","w":"37.647059%","h":"1.568627%","txt":"scientific interests encompassed his-","style":"font-family: Times; color: #231f20; font-size: 13;"},{"x":"52.794118%","y":"76.27451%","w":"37.647059%","h":"1.568627%","txt":"tory of science (psychology in partic-","style":"font-family: Times; color: #231f20; font-size: 13;"},{"x":"52.794118%","y":"77.941176%","w":"38.235294%","h":"1.568627%","txt":"ular), psycholinguistics, theory and ","style":"font-family: Times; color: #231f20; font-size: 13;"},{"x":"52.794118%","y":"79.607843%","w":"37.647059%","h":"1.568627%","txt":"methodology of psychology, psychol-","style":"font-family: Times; color: #231f20; font-size: 13;"},{"x":"52.794118%","y":"81.27451%","w":"18.235294%","h":"1.568627%","txt":"ogy of creativity. ","style":"font-family: Times; color: #231f20; font-size: 13;"},{"x":"52.794118%","y":"83.039216%","w":"38.235294%","h":"1.568627%","txt":"He  was  the  author  of  a  number  of ","style":"font-family: Times; color: #231f20; font-size: 13;"},{"x":"52.794118%","y":"84.705882%","w":"38.235294%","h":"1.568627%","txt":"monographs, most important among ","style":"font-family: Times; color: #231f20; font-size: 13;"},{"x":"52.794118%","y":"86.372549%","w":"38.235294%","h":"1.568627%","txt":"them are: Problems of Determinism ","style":"font-family: Times; color: #231f20; font-size: 13;"},{"x":"52.794118%","y":"88.039216%","w":"37.647059%","h":"1.568627%","txt":"in Psychophysiology of 19th Centu-","style":"font-family: Times; color: #231f20; font-size: 13;"}]