[{"x":"9.264706%","y":"4.411765%","w":"19.117647%","h":"1.470588%","txt":"<i>Наши презентации</i>","style":"font-family: Times; color: #231f20; font-size: 11;"},{"x":"10.147059%","y":"93.333333%","w":"31.617647%","h":"3.627451%","txt":"<b>РАЗВИТИЕ ЛИЧНОСТИ</b>","style":"font-family: Times; color: #ffffff; font-size: 29;"},{"x":"59.264706%","y":"93.823529%","w":"3.235294%","h":"2.352941%","txt":"90","style":"font-family: Times; color: #231f20; font-size: 19;"},{"x":"78.235294%","y":"94.705882%","w":"8.088235%","h":"1.176471%","txt":"<b>№ 4 – 2016</b>","style":"font-family: Times; color: #231f20; font-size: 8;"},{"x":"28.088235%","y":"7.45098%","w":"59.264706%","h":"1.960784%","txt":"развитие идей ученого, но в то же время усилил понима-","style":"font-family: Times; color: #231f20; font-size: 13;"},{"x":"28.088235%","y":"9.215686%","w":"60%","h":"1.960784%","txt":"ние неоспоримой значимости его гения: спустя десятки ","style":"font-family: Times; color: #231f20; font-size: 13;"},{"x":"28.088235%","y":"10.980392%","w":"60%","h":"1.960784%","txt":"лет ученые, ознакомившись с идеями Л.С. Выготского, ","style":"font-family: Times; color: #231f20; font-size: 13;"},{"x":"28.088235%","y":"12.745098%","w":"59.852941%","h":"1.960784%","txt":"ясно  прочувствовали  принципиальную  значимость ","style":"font-family: Times; color: #231f20; font-size: 13;"},{"x":"28.088235%","y":"14.509804%","w":"33.235294%","h":"1.960784%","txt":"открытий великого мыслителя.","style":"font-family: Times; color: #231f20; font-size: 13;"},{"x":"32.5%","y":"16.27451%","w":"55%","h":"1.960784%","txt":"Л.С. Выготский писал: «Жизнь во времени, куль-","style":"font-family: Times; color: #231f20; font-size: 13;"},{"x":"28.088235%","y":"18.137255%","w":"59.264706%","h":"1.960784%","txt":"турное развитие, труд – всё, отличающее в психологиче-","style":"font-family: Times; color: #231f20; font-size: 13;"},{"x":"28.088235%","y":"19.901961%","w":"60%","h":"1.960784%","txt":"ской сфере человека от животного, теснейшим образом ","style":"font-family: Times; color: #231f20; font-size: 13;"},{"x":"28.088235%","y":"21.666667%","w":"60%","h":"1.960784%","txt":"связано с тем фактом, что параллельно с овладением ","style":"font-family: Times; color: #231f20; font-size: 13;"},{"x":"28.088235%","y":"23.431373%","w":"59.852941%","h":"1.960784%","txt":"внешней природой в процессе исторического развития ","style":"font-family: Times; color: #231f20; font-size: 13;"},{"x":"28.088235%","y":"25.196078%","w":"60%","h":"1.960784%","txt":"человека  шло  овладение  собой,  своим  собственным ","style":"font-family: Times; color: #231f20; font-size: 13;"},{"x":"28.088235%","y":"26.960784%","w":"59.852941%","h":"1.960784%","txt":"поведением»  [Там  же,  с.  85].  В  этой  связи  возникает ","style":"font-family: Times; color: #231f20; font-size: 13;"},{"x":"28.088235%","y":"28.72549%","w":"60%","h":"1.960784%","txt":"потребность  повторить  сущностно  значимую  мысль ","style":"font-family: Times; color: #231f20; font-size: 13;"},{"x":"28.088235%","y":"30.588235%","w":"59.264706%","h":"1.960784%","txt":"Ф.М. Достоевского о том, что «человеку надо выделать-","style":"font-family: Times; color: #231f20; font-size: 13;"},{"x":"28.088235%","y":"32.352941%","w":"59.264706%","h":"1.960784%","txt":"ся» [26, с. 47]. Л.С. Выготский соглашался с Ф. Энгель-","style":"font-family: Times; color: #231f20; font-size: 13;"},{"x":"28.088235%","y":"34.117647%","w":"59.264706%","h":"1.960784%","txt":"сом в том, что «труд создал самого человека» [27, с. 486].","style":"font-family: Times; color: #231f20; font-size: 13;"},{"x":"31.029412%","y":"37.254902%","w":"53.529412%","h":"1.470588%","txt":"<b>3.  История развития высших психических функций</b>","style":"font-family: Times; color: #231f20; font-size: 12;"},{"x":"32.5%","y":"39.411765%","w":"55%","h":"1.960784%","txt":"Работа Л.С. Выготского «Развитие высших психиче-","style":"font-family: Times; color: #231f20; font-size: 13;"},{"x":"28.088235%","y":"41.176471%","w":"59.264706%","h":"1.960784%","txt":"ских функций» была закончена в 1931 г., а впервые опу-","style":"font-family: Times; color: #231f20; font-size: 13;"},{"x":"28.088235%","y":"42.941176%","w":"28.970588%","h":"1.960784%","txt":"бликована только в 1960 г. ","style":"font-family: Times; color: #231f20; font-size: 13;"},{"x":"32.5%","y":"44.705882%","w":"55.588235%","h":"1.960784%","txt":"Психолог  апеллировал  к  мыслям  Ф.  Энгельса, ","style":"font-family: Times; color: #231f20; font-size: 13;"},{"x":"28.088235%","y":"46.470588%","w":"59.852941%","h":"1.960784%","txt":"полагавшего,  что  мнение  о  том,  что  «только  природа ","style":"font-family: Times; color: #231f20; font-size: 13;"},{"x":"28.088235%","y":"48.235294%","w":"60%","h":"1.960784%","txt":"действует на человека и что только природные условия ","style":"font-family: Times; color: #231f20; font-size: 13;"},{"x":"28.088235%","y":"50.098039%","w":"59.264706%","h":"1.960784%","txt":"определяют повсюду его историческое развитие, – стра-","style":"font-family: Times; color: #231f20; font-size: 13;"},{"x":"28.088235%","y":"51.862745%","w":"59.264706%","h":"1.960784%","txt":"дает односторонностью и забывает, что и человек воз-","style":"font-family: Times; color: #231f20; font-size: 13;"},{"x":"28.088235%","y":"53.627451%","w":"60%","h":"1.960784%","txt":"действует обратно на природу, изменяет ее, создает себе ","style":"font-family: Times; color: #231f20; font-size: 13;"},{"x":"28.088235%","y":"55.392157%","w":"56.029412%","h":"1.960784%","txt":"новые условия существования» [Там же, с. 545–546]. ","style":"font-family: Times; color: #231f20; font-size: 13;"},{"x":"32.5%","y":"57.156863%","w":"55%","h":"1.960784%","txt":"Л.С. Выготский писал: «Для человеческого приспо-","style":"font-family: Times; color: #231f20; font-size: 13;"},{"x":"28.088235%","y":"58.921569%","w":"60%","h":"1.960784%","txt":"собления  существенно  активное  <i>изменение  природы </i>","style":"font-family: Times; color: #231f20; font-size: 13;"},{"x":"28.088235%","y":"60.686275%","w":"59.264706%","h":"1.960784%","txt":"<i>человека</i>. Оно лежит в основе всей человеческой исто-","style":"font-family: Times; color: #231f20; font-size: 13;"},{"x":"28.088235%","y":"62.54902%","w":"60%","h":"1.960784%","txt":"рии. Оно необходимо предполагает активное изменение ","style":"font-family: Times; color: #231f20; font-size: 13;"},{"x":"28.088235%","y":"64.313725%","w":"60%","h":"1.960784%","txt":"и  поведения  человека»  [8,  с.  80].  При  этом  психолог ","style":"font-family: Times; color: #231f20; font-size: 13;"},{"x":"28.088235%","y":"66.078431%","w":"59.264706%","h":"1.960784%","txt":"обращался  к  идеям  К.  Маркса:  «Воздействуя  посред-","style":"font-family: Times; color: #231f20; font-size: 13;"},{"x":"28.088235%","y":"67.843137%","w":"60%","h":"1.960784%","txt":"ством этого движения на внешнюю природу и изменяя ","style":"font-family: Times; color: #231f20; font-size: 13;"},{"x":"28.088235%","y":"69.607843%","w":"59.264706%","h":"1.960784%","txt":"ее, он в то же время изменяет свою собственную приро-","style":"font-family: Times; color: #231f20; font-size: 13;"},{"x":"28.088235%","y":"71.372549%","w":"60%","h":"1.960784%","txt":"ду. Он развивает дремлющие в ней силы и подчиняет ","style":"font-family: Times; color: #231f20; font-size: 13;"},{"x":"28.088235%","y":"73.235294%","w":"59.264706%","h":"1.960784%","txt":"игру этих сил своей собственной власти» [28, с. 188–189].","style":"font-family: Times; color: #231f20; font-size: 13;"},{"x":"32.5%","y":"75%","w":"55.588235%","h":"1.960784%","txt":"Ссылаясь  на  идеи  К.  Маркса  и  Ф.  Энгельса, ","style":"font-family: Times; color: #231f20; font-size: 13;"},{"x":"28.088235%","y":"76.764706%","w":"59.264706%","h":"1.960784%","txt":"Л.С. Выготский писал: «Но ни из каких природных свя-","style":"font-family: Times; color: #231f20; font-size: 13;"},{"x":"28.088235%","y":"78.529412%","w":"59.264706%","h":"1.960784%","txt":"зей нельзя понять активного приспособления к приро-","style":"font-family: Times; color: #231f20; font-size: 13;"},{"x":"28.088235%","y":"80.294118%","w":"60%","h":"1.960784%","txt":"де, изменения ее человеком. Это можно понять только ","style":"font-family: Times; color: #231f20; font-size: 13;"},{"x":"28.088235%","y":"82.058824%","w":"59.264706%","h":"1.960784%","txt":"из социальной природы человека. Иначе мы возвраща-","style":"font-family: Times; color: #231f20; font-size: 13;"},{"x":"28.088235%","y":"83.823529%","w":"60%","h":"1.960784%","txt":"емся к натуралистическому утверждению, что только ","style":"font-family: Times; color: #231f20; font-size: 13;"},{"x":"28.088235%","y":"85.686275%","w":"59.264706%","h":"1.960784%","txt":"природа действует на человека» [8, с. 81]. При этом пси-","style":"font-family: Times; color: #231f20; font-size: 13;"},{"x":"28.088235%","y":"87.45098%","w":"60%","h":"1.960784%","txt":"холог апеллировал к философу Ф. Энгельсу, который ","style":"font-family: Times; color: #231f20; font-size: 13;"},{"x":"28.088235%","y":"89.215686%","w":"60%","h":"1.960784%","txt":"писал: «Как естествознание, так и философия до сих пор ","style":"font-family: Times; color: #231f20; font-size: 13;"},{"x":"9.264706%","y":"16.470588%","w":"16.617647%","h":"1.568627%","txt":"Жизнь во времени, ","style":"font-family: Times; color: #231f20; font-size: 10;"},{"x":"9.264706%","y":"17.941176%","w":"10.147059%","h":"1.568627%","txt":"культурное ","style":"font-family: Times; color: #231f20; font-size: 10;"},{"x":"9.264706%","y":"19.411765%","w":"14.411765%","h":"1.568627%","txt":"развитие, труд – ","style":"font-family: Times; color: #231f20; font-size: 10;"},{"x":"9.264706%","y":"20.882353%","w":"16.617647%","h":"1.568627%","txt":"условия овладения ","style":"font-family: Times; color: #231f20; font-size: 10;"},{"x":"9.264706%","y":"22.352941%","w":"14.705882%","h":"1.568627%","txt":"человеком своим ","style":"font-family: Times; color: #231f20; font-size: 10;"},{"x":"9.264706%","y":"23.823529%","w":"11.323529%","h":"1.568627%","txt":"собственным ","style":"font-family: Times; color: #231f20; font-size: 10;"},{"x":"9.264706%","y":"25.294118%","w":"10%","h":"1.568627%","txt":"поведением","style":"font-family: Times; color: #231f20; font-size: 10;"},{"x":"9.264706%","y":"39.509804%","w":"10.735294%","h":"1.568627%","txt":"Сущностное ","style":"font-family: Times; color: #231f20; font-size: 10;"},{"x":"9.264706%","y":"40.980392%","w":"18.088235%","h":"1.568627%","txt":"значение изменения ","style":"font-family: Times; color: #231f20; font-size: 10;"},{"x":"9.264706%","y":"42.45098%","w":"9.264706%","h":"1.568627%","txt":"человеком ","style":"font-family: Times; color: #231f20; font-size: 10;"},{"x":"9.264706%","y":"43.921569%","w":"18.088235%","h":"1.568627%","txt":"собственной природы","style":"font-family: Times; color: #231f20; font-size: 10;"},{"x":"9.264706%","y":"75.098039%","w":"8.529412%","h":"1.568627%","txt":"Активное ","style":"font-family: Times; color: #231f20; font-size: 10;"},{"x":"9.264706%","y":"76.568627%","w":"13.970588%","h":"1.568627%","txt":"приспособление ","style":"font-family: Times; color: #231f20; font-size: 10;"},{"x":"9.264706%","y":"78.039216%","w":"15%","h":"1.568627%","txt":"к природе можно ","style":"font-family: Times; color: #231f20; font-size: 10;"},{"x":"9.264706%","y":"79.509804%","w":"6.323529%","h":"1.568627%","txt":"понять ","style":"font-family: Times; color: #231f20; font-size: 10;"},{"x":"9.264706%","y":"80.980392%","w":"12.794118%","h":"1.568627%","txt":"из социальной ","style":"font-family: Times; color: #231f20; font-size: 10;"},{"x":"9.264706%","y":"82.45098%","w":"15.588235%","h":"1.568627%","txt":"природы человека","style":"font-family: Times; color: #231f20; font-size: 10;"}]